Workbook
Name Fact_Инвестиции: Fact_Инвестиции!$A$1:$I$41

Sheet Лист5
A2: Год | B2: 2024
A3: Категория | B3: (Все)
B5: Название фонда
B6: Сумма по полю СЧА | F6: Сумма по полю КоличествоПаев | J6: Итог Сумма по полю СЧА | K6: Итог Сумма по полю КоличествоПаев
A7: № месяца | B7: Apple | C7: Microsoft | D7: Газпромбанк-10 | E7: ОФЗ 26231 | F7: Apple | G7: Microsoft | H7: Газпромбанк-10 | I7: ОФЗ 26231
A8: 1 | B8: 1482000 | C8: 48000000 | D8: 215027900 | E8: 54683600 | F8: 8000 | G8: 15000 | H8: 102000 | I8: 52000 | J8: 319193500 | K8: 177000
A9: 2 | B9: 1619250 | C9: 51608000 | D9: 112831700 | E9: 23380500 | F9: 8500 | G9: 16000 | H9: 53000 | I9: 22000 | J9: 189439450 | K9: 99500
A10: 3 | B10: 1761750 | C10: 55250000 | D10: 118008000 | E10: 26755000 | F10: 9000 | G10: 17000 | H10: 55000 | I10: 25000 | J10: 201774750 | K10: 106000
A11: 4 | B11: 1902850 | C11: 59044500 | E11: 30209200 | F11: 9500 | G11: 18000 | I11: 28000 | J11: 91156550 | K11: 55500
A12: 5 | B12: 2058000 | C12: 66315000 | D12: 125477200 | F12: 10000 | G12: 20000 | H12: 58000 | J12: 193850200 | K12: 88000
A13: 6 | D13: 130974000 | E13: 32568000 | H13: 60000 | I13: 30000 | J13: 163542000 | K13: 90000
A14: 7 | B14: 2312750 | C14: 73700000 | F14: 11000 | G14: 22000 | J14: 76012750 | K14: 33000
A15: 8 | D15: 136734800 | E15: 38335500 | H15: 62000 | I15: 35000 | J15: 175070300 | K15: 97000
A16: 9 | B16: 2590800 | C16: 81246000 | F16: 12000 | G16: 24000 | J16: 83836800 | K16: 36000
A17: 10 | D17: 144859000 | E17: 44350000 | H17: 65000 | I17: 40000 | J17: 189209000 | K17: 105000
A18: 11 | B18: 2879500 | C18: 88940800 | F18: 13000 | G18: 26000 | J18: 91820300 | K18: 39000
A19: 12 | B19: 3202500 | C19: 96887000 | D19: 312900200 | E19: 107783000 | F19: 14000 | G19: 28000 | H19: 138000 | I19: 95000 | J19: 520772700 | K19: 275000
A20: Общий итог | B20: 19809400 | C20: 620991300 | D20: 1296812800 | E20: 358064800 | F20: 95000 | G20: 186000 | H20: 593000 | I20: 327000 | J20: 2295678300 | K20: 1201000

Sheet Fact_Инвестиции
A1: КодСобытия | B1: КодВремени | C1: КодФонда | D1: КодИнвестора | E1: КодЦеннойБумаги | F1: КоличествоПаев | G1: СтоимостьПая | H1: СЧА | I1: Доходность | J1: Тип | K1: Идентификатор | L1: Наименование_ФИО | M1: Категория | N1: Регион | O1: ISIN_FIGI | P1: Наименование | Q1: Номинал | R1: ВалютаНоминала | S1: ДатаПогашения | T1: ТипБумаги | U1: Название | V1: ISIN | W1: ДатаСоздания | X1: Статус | Y1: Валюта | Z1: Дата | AA1: Год | AB1: Квартал | AC1: Месяц | AD1: День | AE1: ДеньНедели
A2: 1 | B2: 20240101 | C2: 1 | D2: 1 | E2: 1 | F2: 10000 | G2: 1050.5 | H2: 10505000 | I2: 7.2 | J2: =VLOOKUP($D2,Инвестор!$A$2:$F$6,COLUMN(Fact_Инвестиции!B2),0) -> Физическое лицо | K2: =VLOOKUP($D2,Инвестор!$A$2:$F$6,COLUMN(Fact_Инвестиции!C2),0) -> 770112345678 | L2: =VLOOKUP($D2,Инвестор!$A$2:$F$6,COLUMN(Fact_Инвестиции!D2),0) -> Иванов Алексей Петрович | M2: =VLOOKUP($D2,Инвестор!$A$2:$F$6,COLUMN(Fact_Инвестиции!E2),0) -> Квалифицированный | N2: =VLOOKUP($D2,Инвестор!$A$2:$F$6,COLUMN(Fact_Инвестиции!F2),0) -> Москва | O2: =VLOOKUP($C2,Фонд!$A$2:$H$7,COLUMN(Fact_Инвестиции!B2),0) -> RU000A0JXYF1 | P2: =VLOOKUP($C2,Фонд!$A$2:$H$7,COLUMN(Fact_Инвестиции!C2),0) -> ОФЗ 26231 | Q2: =VLOOKUP($C2,Фонд!$A$2:$H$7,COLUMN(Fact_Инвестиции!D2),0) -> 1000 | R2: =VLOOKUP($C2,Фонд!$A$2:$H$7,COLUMN(Fact_Инвестиции!E2),0) -> RUB | S2: =VLOOKUP($C2,Фонд!$A$2:$H$7,COLUMN(Fact_Инвестиции!F2),0) -> 47848 | T2: =VLOOKUP($C2,Фонд!$A$2:$H$7,COLUMN(Fact_Инвестиции!G2),0) -> Гос. облигация | U2: =VLOOKUP($E2,Фонд!$A$2:$H$7,COLUMN(Fact_Инвестиции!B2),0) -> RU000A0JXYF1 | V2: =VLOOKUP($E2,Фонд!$A$2:$H$7,COLUMN(Fact_Инвестиции!C2),0) -> ОФЗ 26231 | W2: =VLOOKUP($E2,Фонд!$A$2:$H$7,COLUMN(Fact_Инвестиции!D2),0) -> 1000 | X2: =VLOOKUP($E2,Фонд!$A$2:$H$7,COLUMN(Fact_Инвестиции!E2),0) -> RUB | Y2: =VLOOKUP($E2,Фонд!$A$2:$H$7,COLUMN(Fact_Инвестиции!F2),0) -> 47848 | Z2: =VLOOKUP($B2,Время!$A$2:$G$25,COLUMN(Fact_Инвестиции!B2),0) -> 45292 | AA2: =VLOOKUP($B2,Время!$A$2:$G$25,COLUMN(Fact_Инвестиции!C2),0) -> 2024 | AB2: =VLOOKUP($B2,Время!$A$2:$G$25,COLUMN(Fact_Инвестиции!D2),0) -> 1 | AC2: =VLOOKUP($B2,Время!$A$2:$G$25,COLUMN(Fact_Инвестиции!E2),0) -> 1 | AD2: =VLOOKUP($B2,Время!$A$2:$G$25,COLUMN(Fact_Инвестиции!F2),0) -> 1 | AE2: =VLOOKUP($B2,Время!$A$2:$G$25,COLUMN(Fact_Инвестиции!G2),0) -> Понедельник
A3: 2 | B3: 20240101 | C3: 2 | D3: 2 | E3: 2 | F3: 50000 | G3: 2100.75 | H3: 105037500 | I3: 8.5 | J3: =VLOOKUP($D3,Инвестор!$A$2:$F$6,COLUMN(Fact_Инвестиции!B3),0) -> Юридическое лицо | K3: =VLOOKUP($D3,Инвестор!$A$2:$F$6,COLUMN(Fact_Инвестиции!C3),0) -> 770198765432 | L3: =VLOOKUP($D3,Инвестор!$A$2:$F$6,COLUMN(Fact_Инвестиции!D3),0) -> ООО "ИнвестПро" | M3: =VLOOKUP($D3,Инвестор!$A$2:$F$6,COLUMN(Fact_Инвестиции!E3),0) -> Профессиональный | N3: =VLOOKUP($D3,Инвестор!$A$2:$F$6,COLUMN(Fact_Инвестиции!F3),0) -> Санкт-Петербург | O3: =VLOOKUP($C3,Фонд!$A$2:$H$7,COLUMN(Fact_Инвестиции!B3),0) -> RU000A0JX0F2 | P3: =VLOOKUP($C3,Фонд!$A$2:$H$7,COLUMN(Fact_Инвестиции!C3),0) -> Газпромбанк-10 | Q3: =VLOOKUP($C3,Фонд!$A$2:$H$7,COLUMN(Fact_Инвестиции!D3),0) -> 1000 | R3: =VLOOKUP($C3,Фонд!$A$2:$H$7,COLUMN(Fact_Инвестиции!E3),0) -> RUB | S3: =VLOOKUP($C3,Фонд!$A$2:$H$7,COLUMN(Fact_Инвестиции!F3),0) -> 46888 | T3: =VLOOKUP($C3,Фонд!$A$2:$H$7,COLUMN(Fact_Инвестиции!G3),0) -> Корп. облигация | U3: =VLOOKUP($E3,Фонд!$A$2:$H$7,COLUMN(Fact_Инвестиции!B3),0) -> RU000A0JX0F2 | V3: =VLOOKUP($E3,Фонд!$A$2:$H$7,COLUMN(Fact_Инвестиции!C3),0) -> Газпромбанк-10 | W3: =VLOOKUP($E3,Фонд!$A$2:$H$7,COLUMN(Fact_Инвестиции!D3),0) -> 1000 | X3: =VLOOKUP($E3,Фонд!$A$2:$H$7,COLUMN(Fact_Инвестиции!E3),0) -> RUB | Y3: =VLOOKUP($E3,Фонд!$A$2:$H$7,COLUMN(Fact_Инвестиции!F3),0) -> 46888 | Z3: =VLOOKUP($B3,Время!$A$2:$G$25,COLUMN(Fact_Инвестиции!B3),0) -> 45292 | AA3: =VLOOKUP($B3,Время!$A$2:$G$25,COLUMN(Fact_Инвестиции!C3),0) -> 2024 | AB3: =VLOOKUP($B3,Время!$A$2:$G$25,COLUMN(Fact_Инвестиции!D3),0) -> 1 | AC3: =VLOOKUP($B3,Время!$A$2:$G$25,COLUMN(Fact_Инвестиции!E3),0) -> 1 | AD3: =VLOOKUP($B3,Время!$A$2:$G$25,COLUMN(Fact_Инвестиции!F3),0) -> 1 | AE3: =VLOOKUP($B3,Время!$A$2:$G$25,COLUMN(Fact_Инвестиции!G3),0) -> Понедельник
A4: 3 | B4: 20240101 | C4: 3 | D4: 3 | E4: 3 | F4: 8000 | G4: 185.25 | H4: 1482000 | I4: 12.3 | J4: =VLOOKUP($D4,Инвестор!$A$2:$F$6,COLUMN(Fact_Инвестиции!B4),0) -> Физическое лицо | K4: =VLOOKUP($D4,Инвестор!$A$2:$F$6,COLUMN(Fact_Инвестиции!C4),0) -> 770123456789 | L4: =VLOOKUP($D4,Инвестор!$A$2:$F$6,COLUMN(Fact_Инвестиции!D4),0) -> Смирнова Мария Игоревна | M4: =VLOOKUP($D4,Инвестор!$A$2:$F$6,COLUMN(Fact_Инвестиции!E4),0) -> Неквалифицированный | N4: =VLOOKUP($D4,Инвестор!$A$2:$F$6,COLUMN(Fact_Инвестиции!F4),0) -> Новосибирск | O4: =VLOOKUP($C4,Фонд!$A$2:$H$7,COLUMN(Fact_Инвестиции!B4),0) -> US0378331005 | P4: =VLOOKUP($C4,Фонд!$A$2:$H$7,COLUMN(Fact_Инвестиции!C4),0) -> Apple | Q4: =VLOOKUP($C4,Фонд!$A$2:$H$7,COLUMN(Fact_Инвестиции!D4),0) -> 0 | R4: =VLOOKUP($C4,Фонд!$A$2:$H$7,COLUMN(Fact_Инвестиции!E4),0) -> USD | S4: =VLOOKUP($C4,Фонд!$A$2:$H$7,COLUMN(Fact_Инвестиции!F4),0) -> 0 | T4: =VLOOKUP($C4,Фонд!$A$2:$H$7,COLUMN(Fact_Инвестиции!G4),0) -> Акция | U4: =VLOOKUP($E4,Фонд!$A$2:$H$7,COLUMN(Fact_Инвестиции!B4),0) -> US0378331005 | V4: =VLOOKUP($E4,Фонд!$A$2:$H$7,COLUMN(Fact_Инвестиции!C4),0) -> Apple | W4: =VLOOKUP($E4,Фонд!$A$2:$H$7,COLUMN(Fact_Инвестиции!D4),0) -> 0 | X4: =VLOOKUP($E4,Фонд!$A$2:$H$7,COLUMN(Fact_Инвестиции!E4),0) -> USD | Y4: =VLOOKUP($E4,Фонд!$A$2:$H$7,COLUMN(Fact_Инвестиции!F4),0) -> 0 | Z4: =VLOOKUP($B4,Время!$A$2:$G$25,COLUMN(Fact_Инвестиции!B4),0) -> 45292 | AA4: =VLOOKUP($B4,Время!$A$2:$G$25,COLUMN(Fact_Инвестиции!C4),0) -> 2024 | AB4: =VLOOKUP($B4,Время!$A$2:$G$25,COLUMN(Fact_Инвестиции!D4),0) -> 1 | AC4: =VLOOKUP($B4,Время!$A$2:$G$25,COLUMN(Fact_Инвестиции!E4),0) -> 1 | AD4: =VLOOKUP($B4,Время!$A$2:$G$25,COLUMN(Fact_Инвестиции!F4),0) -> 1 | AE4: =VLOOKUP($B4,Время!$A$2:$G$25,COLUMN(Fact_Инвестиции!G4),0) -> Понедельник
A5: 5 | B5: 20240101 | C5: 4 | D5: 4 | E5: 4 | F5: 15000 | G5: 3200 | H5: 48000000 | I5: 6.8 | J5: =VLOOKUP($D5,Инвестор!$A$2:$F$6,COLUMN(Fact_Инвестиции!B5),0) -> Юридическое лицо | K5: =VLOOKUP($D5,Инвестор!$A$2:$F$6,COLUMN(Fact_Инвестиции!C5),0) -> 770187654321 | L5: =VLOOKUP($D5,Инвестор!$A$2:$F$6,COLUMN(Fact_Инвестиции!D5),0) -> АО "КапиталТраст" | M5: =VLOOKUP($D5,Инвестор!$A$2:$F$6,COLUMN(Fact_Инвестиции!E5),0) -> Профессиональный | N5: =VLOOKUP($D5,Инвестор!$A$2:$F$6,COLUMN(Fact_Инвестиции!F5),0) -> Москва | O5: =VLOOKUP($C5,Фонд!$A$2:$H$7,COLUMN(Fact_Инвестиции!B5),0) -> US5949181045 | P5: =VLOOKUP($C5,Фонд!$A$2:$H$7,COLUMN(Fact_Инвестиции!C5),0) -> Microsoft | Q5: =VLOOKUP($C5,Фонд!$A$2:$H$7,COLUMN(Fact_Инвестиции!D5),0) -> 0 | R5: =VLOOKUP($C5,Фонд!$A$2:$H$7,COLUMN(Fact_Инвестиции!E5),0) -> USD | S5: =VLOOKUP($C5,Фонд!$A$2:$H$7,COLUMN(Fact_Инвестиции!F5),0) -> 0 | T5: =VLOOKUP($C5,Фонд!$A$2:$H$7,COLUMN(Fact_Инвестиции!G5),0) -> Акция | U5: =VLOOKUP($E5,Фонд!$A$2:$H$7,COLUMN(Fact_Инвестиции!B5),0) -> US5949181045 | V5: =VLOOKUP($E5,Фонд!$A$2:$H$7,COLUMN(Fact_Инвестиции!C5),0) -> Microsoft | W5: =VLOOKUP($E5,Фонд!$A$2:$H$7,COLUMN(Fact_Инвестиции!D5),0) -> 0 | X5: =VLOOKUP($E5,Фонд!$A$2:$H$7,COLUMN(Fact_Инвестиции!E5),0) -> USD | Y5: =VLOOKUP($E5,Фонд!$A$2:$H$7,COLUMN(Fact_Инвестиции!F5),0) -> 0 | Z5: =VLOOKUP($B5,Время!$A$2:$G$25,COLUMN(Fact_Инвестиции!B5),0) -> 45292 | AA5: =VLOOKUP($B5,Время!$A$2:$G$25,COLUMN(Fact_Инвестиции!C5),0) -> 2024 | AB5: =VLOOKUP($B5,Время!$A$2:$G$25,COLUMN(Fact_Инвестиции!D5),0) -> 1 | AC5: =VLOOKUP($B5,Время!$A$2:$G$25,COLUMN(Fact_Инвестиции!E5),0) -> 1 | AD5: =VLOOKUP($B5,Время!$A$2:$G$25,COLUMN(Fact_Инвестиции!F5),0) -> 1 | AE5: =VLOOKUP($B5,Время!$A$2:$G$25,COLUMN(Fact_Инвестиции!G5),0) -> Понедельник
A6: 6 | B6: 20240101 | C6: 1 | D6: 5 | E6: 1 | F6: 20000 | G6: 1050.5 | H6: 21010000 | I6: 7.2 | J6: =VLOOKUP($D6,Инвестор!$A$2:$F$6,COLUMN(Fact_Инвестиции!B6),0) -> Физическое лицо | K6: =VLOOKUP($D6,Инвестор!$A$2:$F$6,COLUMN(Fact_Инвестиции!C6),0) -> 770134567890 | L6: =VLOOKUP($D6,Инвестор!$A$2:$F$6,COLUMN(Fact_Инвестиции!D6),0) -> Кузнецов Дмитрий Сергеевич | M6: =VLOOKUP($D6,Инвестор!$A$2:$F$6,COLUMN(Fact_Инвестиции!E6),0) -> Квалифицированный | N6: =VLOOKUP($D6,Инвестор!$A$2:$F$6,COLUMN(Fact_Инвестиции!F6),0) -> Екатеринбург | O6: =VLOOKUP($C6,Фонд!$A$2:$H$7,COLUMN(Fact_Инвестиции!B6),0) -> RU000A0JXYF1 | P6: =VLOOKUP($C6,Фонд!$A$2:$H$7,COLUMN(Fact_Инвестиции!C6),0) -> ОФЗ 26231 | Q6: =VLOOKUP($C6,Фонд!$A$2:$H$7,COLUMN(Fact_Инвестиции!D6),0) -> 1000 | R6: =VLOOKUP($C6,Фонд!$A$2:$H$7,COLUMN(Fact_Инвестиции!E6),0) -> RUB | S6: =VLOOKUP($C6,Фонд!$A$2:$H$7,COLUMN(Fact_Инвестиции!F6),0) -> 47848 | T6: =VLOOKUP($C6,Фонд!$A$2:$H$7,COLUMN(Fact_Инвестиции!G6),0) -> Гос. облигация | U6: =VLOOKUP($E6,Фонд!$A$2:$H$7,COLUMN(Fact_Инвестиции!B6),0) -> RU000A0JXYF1 | V6: =VLOOKUP($E6,Фонд!$A$2:$H$7,COLUMN(Fact_Инвестиции!C6),0) -> ОФЗ 26231 | W6: =VLOOKUP($E6,Фонд!$A$2:$H$7,COLUMN(Fact_Инвестиции!D6),0) -> 1000 | X6: =VLOOKUP($E6,Фонд!$A$2:$H$7,COLUMN(Fact_Инвестиции!E6),0) -> RUB | Y6: =VLOOKUP($E6,Фонд!$A$2:$H$7,COLUMN(Fact_Инвестиции!F6),0) -> 47848 | Z6: =VLOOKUP($B6,Время!$A$2:$G$25,COLUMN(Fact_Инвестиции!B6),0) -> 45292 | AA6: =VLOOKUP($B6,Время!$A$2:$G$25,COLUMN(Fact_Инвестиции!C6),0) -> 2024 | AB6: =VLOOKUP($B6,Время!$A$2:$G$25,COLUMN(Fact_Инвестиции!D6),0) -> 1 | AC6: =VLOOKUP($B6,Время!$A$2:$G$25,COLUMN(Fact_Инвестиции!E6),0) -> 1 | AD6: =VLOOKUP($B6,Время!$A$2:$G$25,COLUMN(Fact_Инвестиции!F6),0) -> 1 | AE6: =VLOOKUP($B6,Время!$A$2:$G$25,COLUMN(Fact_Инвестиции!G6),0) -> Понедельник
A7: 7 | B7: 20240115 | C7: 1 | D7: 1 | E7: 1 | F7: 12000 | G7: 1055.3 | H7: 12663600 | I7: 7.5 | J7: =VLOOKUP($D7,Инвестор!$A$2:$F$6,COLUMN(Fact_Инвестиции!B7),0) -> Физическое лицо | K7: =VLOOKUP($D7,Инвестор!$A$2:$F$6,COLUMN(Fact_Инвестиции!C7),0) -> 770112345678 | L7: =VLOOKUP($D7,Инвестор!$A$2:$F$6,COLUMN(Fact_Инвестиции!D7),0) -> Иванов Алексей Петрович | M7: =VLOOKUP($D7,Инвестор!$A$2:$F$6,COLUMN(Fact_Инвестиции!E7),0) -> Квалифицированный | N7: =VLOOKUP($D7,Инвестор!$A$2:$F$6,COLUMN(Fact_Инвестиции!F7),0) -> Москва | O7: =VLOOKUP($C7,Фонд!$A$2:$H$7,COLUMN(Fact_Инвестиции!B7),0) -> RU000A0JXYF1 | P7: =VLOOKUP($C7,Фонд!$A$2:$H$7,COLUMN(Fact_Инвестиции!C7),0) -> ОФЗ 26231 | Q7: =VLOOKUP($C7,Фонд!$A$2:$H$7,COLUMN(Fact_Инвестиции!D7),0) -> 1000 | R7: =VLOOKUP($C7,Фонд!$A$2:$H$7,COLUMN(Fact_Инвестиции!E7),0) -> RUB | S7: =VLOOKUP($C7,Фонд!$A$2:$H$7,COLUMN(Fact_Инвестиции!F7),0) -> 47848 | T7: =VLOOKUP($C7,Фонд!$A$2:$H$7,COLUMN(Fact_Инвестиции!G7),0) -> Гос. облигация | U7: =VLOOKUP($E7,Фонд!$A$2:$H$7,COLUMN(Fact_Инвестиции!B7),0) -> RU000A0JXYF1 | V7: =VLOOKUP($E7,Фонд!$A$2:$H$7,COLUMN(Fact_Инвестиции!C7),0) -> ОФЗ 26231 | W7: =VLOOKUP($E7,Фонд!$A$2:$H$7,COLUMN(Fact_Инвестиции!D7),0) -> 1000 | X7: =VLOOKUP($E7,Фонд!$A$2:$H$7,COLUMN(Fact_Инвестиции!E7),0) -> RUB | Y7: =VLOOKUP($E7,Фонд!$A$2:$H$7,COLUMN(Fact_Инвестиции!F7),0) -> 47848 | Z7: =VLOOKUP($B7,Время!$A$2:$G$25,COLUMN(Fact_Инвестиции!B7),0) -> 45306 | AA7: =VLOOKUP($B7,Время!$A$2:$G$25,COLUMN(Fact_Инвестиции!C7),0) -> 2024 | AB7: =VLOOKUP($B7,Время!$A$2:$G$25,COLUMN(Fact_Инвестиции!D7),0) -> 1 | AC7: =VLOOKUP($B7,Время!$A$2:$G$25,COLUMN(Fact_Инвестиции!E7),0) -> 1 | AD7: =VLOOKUP($B7,Время!$A$2:$G$25,COLUMN(Fact_Инвестиции!F7),0) -> 15 | AE7: =VLOOKUP($B7,Время!$A$2:$G$25,COLUMN(Fact_Инвестиции!G7),0) -> Понедельник
A8: 8 | B8: 20240115 | C8: 2 | D8: 2 | E8: 2 | F8: 52000 | G8: 2115.2 | H8: 109990400 | I8: 8.8 | J8: =VLOOKUP($D8,Инвестор!$A$2:$F$6,COLUMN(Fact_Инвестиции!B8),0) -> Юридическое лицо | K8: =VLOOKUP($D8,Инвестор!$A$2:$F$6,COLUMN(Fact_Инвестиции!C8),0) -> 770198765432 | L8: =VLOOKUP($D8,Инвестор!$A$2:$F$6,COLUMN(Fact_Инвестиции!D8),0) -> ООО "ИнвестПро" | M8: =VLOOKUP($D8,Инвестор!$A$2:$F$6,COLUMN(Fact_Инвестиции!E8),0) -> Профессиональный | N8: =VLOOKUP($D8,Инвестор!$A$2:$F$6,COLUMN(Fact_Инвестиции!F8),0) -> Санкт-Петербург | O8: =VLOOKUP($C8,Фонд!$A$2:$H$7,COLUMN(Fact_Инвестиции!B8),0) -> RU000A0JX0F2 | P8: =VLOOKUP($C8,Фонд!$A$2:$H$7,COLUMN(Fact_Инвестиции!C8),0) -> Газпромбанк-10 | Q8: =VLOOKUP($C8,Фонд!$A$2:$H$7,COLUMN(Fact_Инвестиции!D8),0) -> 1000 | R8: =VLOOKUP($C8,Фонд!$A$2:$H$7,COLUMN(Fact_Инвестиции!E8),0) -> RUB | S8: =VLOOKUP($C8,Фонд!$A$2:$H$7,COLUMN(Fact_Инвестиции!F8),0) -> 46888 | T8: =VLOOKUP($C8,Фонд!$A$2:$H$7,COLUMN(Fact_Инвестиции!G8),0) -> Корп. облигация | U8: =VLOOKUP($E8,Фонд!$A$2:$H$7,COLUMN(Fact_Инвестиции!B8),0) -> RU000A0JX0F2 | V8: =VLOOKUP($E8,Фонд!$A$2:$H$7,COLUMN(Fact_Инвестиции!C8),0) -> Газпромбанк-10 | W8: =VLOOKUP($E8,Фонд!$A$2:$H$7,COLUMN(Fact_Инвестиции!D8),0) -> 1000 | X8: =VLOOKUP($E8,Фонд!$A$2:$H$7,COLUMN(Fact_Инвестиции!E8),0) -> RUB | Y8: =VLOOKUP($E8,Фонд!$A$2:$H$7,COLUMN(Fact_Инвестиции!F8),0) -> 46888 | Z8: =VLOOKUP($B8,Время!$A$2:$G$25,COLUMN(Fact_Инвестиции!B8),0) -> 45306 | AA8: =VLOOKUP($B8,Время!$A$2:$G$25,COLUMN(Fact_Инвестиции!C8),0) -> 2024 | AB8: =VLOOKUP($B8,Время!$A$2:$G$25,COLUMN(Fact_Инвестиции!D8),0) -> 1 | AC8: =VLOOKUP($B8,Время!$A$2:$G$25,COLUMN(Fact_Инвестиции!E8),0) -> 1 | AD8: =VLOOKUP($B8,Время!$A$2:$G$25,COLUMN(Fact_Инвестиции!F8),0) -> 15 | AE8: =VLOOKUP($B8,Время!$A$2:$G$25,COLUMN(Fact_Инвестиции!G8),0) -> Понедельник
A9: 9 | B9: 20240201 | C9: 3 | D9: 3 | E9: 3 | F9: 8500 | G9: 190.5 | H9: 1619250 | I9: 13.1 | J9: =VLOOKUP($D9,Инвестор!$A$2:$F$6,COLUMN(Fact_Инвестиции!B9),0) -> Физическое лицо | K9: =VLOOKUP($D9,Инвестор!$A$2:$F$6,COLUMN(Fact_Инвестиции!C9),0) -> 770123456789 | L9: =VLOOKUP($D9,Инвестор!$A$2:$F$6,COLUMN(Fact_Инвестиции!D9),0) -> Смирнова Мария Игоревна | M9: =VLOOKUP($D9,Инвестор!$A$2:$F$6,COLUMN(Fact_Инвестиции!E9),0) -> Неквалифицированный | N9: =VLOOKUP($D9,Инвестор!$A$2:$F$6,COLUMN(Fact_Инвестиции!F9),0) -> Новосибирск | O9: =VLOOKUP($C9,Фонд!$A$2:$H$7,COLUMN(Fact_Инвестиции!B9),0) -> US0378331005 | P9: =VLOOKUP($C9,Фонд!$A$2:$H$7,COLUMN(Fact_Инвестиции!C9),0) -> Apple | Q9: =VLOOKUP($C9,Фонд!$A$2:$H$7,COLUMN(Fact_Инвестиции!D9),0) -> 0 | R9: =VLOOKUP($C9,Фонд!$A$2:$H$7,COLUMN(Fact_Инвестиции!E9),0) -> USD | S9: =VLOOKUP($C9,Фонд!$A$2:$H$7,COLUMN(Fact_Инвестиции!F9),0) -> 0 | T9: =VLOOKUP($C9,Фонд!$A$2:$H$7,COLUMN(Fact_Инвестиции!G9),0) -> Акция | U9: =VLOOKUP($E9,Фонд!$A$2:$H$7,COLUMN(Fact_Инвестиции!B9),0) -> US0378331005 | V9: =VLOOKUP($E9,Фонд!$A$2:$H$7,COLUMN(Fact_Инвестиции!C9),0) -> Apple | W9: =VLOOKUP($E9,Фонд!$A$2:$H$7,COLUMN(Fact_Инвестиции!D9),0) -> 0 | X9: =VLOOKUP($E9,Фонд!$A$2:$H$7,COLUMN(Fact_Инвестиции!E9),0) -> USD | Y9: =VLOOKUP($E9,Фонд!$A$2:$H$7,COLUMN(Fact_Инвестиции!F9),0) -> 0 | Z9: =VLOOKUP($B9,Время!$A$2:$G$25,COLUMN(Fact_Инвестиции!B9),0) -> 45293 | AA9: =VLOOKUP($B9,Время!$A$2:$G$25,COLUMN(Fact_Инвестиции!C9),0) -> 2024 | AB9: =VLOOKUP($B9,Время!$A$2:$G$25,COLUMN(Fact_Инвестиции!D9),0) -> 1 | AC9: =VLOOKUP($B9,Время!$A$2:$G$25,COLUMN(Fact_Инвестиции!E9),0) -> 2 | AD9: =VLOOKUP($B9,Время!$A$2:$G$25,COLUMN(Fact_Инвестиции!F9),0) -> 1 | AE9: =VLOOKUP($B9,Время!$A$2:$G$25,COLUMN(Fact_Инвестиции!G9),0) -> Четверг
A10: 10 | B10: 20240201 | C10: 4 | D10: 4 | E10: 4 | F10: 16000 | G10: 3225.5 | H10: 51608000 | I10: 7.2 | J10: =VLOOKUP($D10,Инвестор!$A$2:$F$6,COLUMN(Fact_Инвестиции!B10),0) -> Юридическое лицо | K10: =VLOOKUP($D10,Инвестор!$A$2:$F$6,COLUMN(Fact_Инвестиции!C10),0) -> 770187654321 | L10: =VLOOKUP($D10,Инвестор!$A$2:$F$6,COLUMN(Fact_Инвестиции!D10),0) -> АО "КапиталТраст" | M10: =VLOOKUP($D10,Инвестор!$A$2:$F$6,COLUMN(Fact_Инвестиции!E10),0) -> Профессиональный | N10: =VLOOKUP($D10,Инвестор!$A$2:$F$6,COLUMN(Fact_Инвестиции!F10),0) -> Москва | O10: =VLOOKUP($C10,Фонд!$A$2:$H$7,COLUMN(Fact_Инвестиции!B10),0) -> US5949181045 | P10: =VLOOKUP($C10,Фонд!$A$2:$H$7,COLUMN(Fact_Инвестиции!C10),0) -> Microsoft | Q10: =VLOOKUP($C10,Фонд!$A$2:$H$7,COLUMN(Fact_Инвестиции!D10),0) -> 0 | R10: =VLOOKUP($C10,Фонд!$A$2:$H$7,COLUMN(Fact_Инвестиции!E10),0) -> USD | S10: =VLOOKUP($C10,Фонд!$A$2:$H$7,COLUMN(Fact_Инвестиции!F10),0) -> 0 | T10: =VLOOKUP($C10,Фонд!$A$2:$H$7,COLUMN(Fact_Инвестиции!G10),0) -> Акция | U10: =VLOOKUP($E10,Фонд!$A$2:$H$7,COLUMN(Fact_Инвестиции!B10),0) -> US5949181045 | V10: =VLOOKUP($E10,Фонд!$A$2:$H$7,COLUMN(Fact_Инвестиции!C10),0) -> Microsoft | W10: =VLOOKUP($E10,Фонд!$A$2:$H$7,COLUMN(Fact_Инвестиции!D10),0) -> 0 | X10: =VLOOKUP($E10,Фонд!$A$2:$H$7,COLUMN(Fact_Инвестиции!E10),0) -> USD | Y10: =VLOOKUP($E10,Фонд!$A$2:$H$7,COLUMN(Fact_Инвестиции!F10),0) -> 0 | Z10: =VLOOKUP($B10,Время!$A$2:$G$25,COLUMN(Fact_Инвестиции!B10),0) -> 45293 | AA10: =VLOOKUP($B10,Время!$A$2:$G$25,COLUMN(Fact_Инвестиции!C10),0) -> 2024 | AB10: =VLOOKUP($B10,Время!$A$2:$G$25,COLUMN(Fact_Инвестиции!D10),0) -> 1 | AC10: =VLOOKUP($B10,Время!$A$2:$G$25,COLUMN(Fact_Инвестиции!E10),0) -> 2 | AD10: =VLOOKUP($B10,Время!$A$2:$G$25,COLUMN(Fact_Инвестиции!F10),0) -> 1 | AE10: =VLOOKUP($B10,Время!$A$2:$G$25,COLUMN(Fact_Инвестиции!G10),0) -> Четверг
A11: 11 | B11: 20240215 | C11: 1 | D11: 5 | E11: 1 | F11: 22000 | G11: 1062.75 | H11: 23380500 | I11: 7.9 | J11: =VLOOKUP($D11,Инвестор!$A$2:$F$6,COLUMN(Fact_Инвестиции!B11),0) -> Физическое лицо | K11: =VLOOKUP($D11,Инвестор!$A$2:$F$6,COLUMN(Fact_Инвестиции!C11),0) -> 770134567890 | L11: =VLOOKUP($D11,Инвестор!$A$2:$F$6,COLUMN(Fact_Инвестиции!D11),0) -> Кузнецов Дмитрий Сергеевич | M11: =VLOOKUP($D11,Инвестор!$A$2:$F$6,COLUMN(Fact_Инвестиции!E11),0) -> Квалифицированный | N11: =VLOOKUP($D11,Инвестор!$A$2:$F$6,COLUMN(Fact_Инвестиции!F11),0) -> Екатеринбург | O11: =VLOOKUP($C11,Фонд!$A$2:$H$7,COLUMN(Fact_Инвестиции!B11),0) -> RU000A0JXYF1 | P11: =VLOOKUP($C11,Фонд!$A$2:$H$7,COLUMN(Fact_Инвестиции!C11),0) -> ОФЗ 26231 | Q11: =VLOOKUP($C11,Фонд!$A$2:$H$7,COLUMN(Fact_Инвестиции!D11),0) -> 1000 | R11: =VLOOKUP($C11,Фонд!$A$2:$H$7,COLUMN(Fact_Инвестиции!E11),0) -> RUB | S11: =VLOOKUP($C11,Фонд!$A$2:$H$7,COLUMN(Fact_Инвестиции!F11),0) -> 47848 | T11: =VLOOKUP($C11,Фонд!$A$2:$H$7,COLUMN(Fact_Инвестиции!G11),0) -> Гос. облигация | U11: =VLOOKUP($E11,Фонд!$A$2:$H$7,COLUMN(Fact_Инвестиции!B11),0) -> RU000A0JXYF1 | V11: =VLOOKUP($E11,Фонд!$A$2:$H$7,COLUMN(Fact_Инвестиции!C11),0) -> ОФЗ 26231 | W11: =VLOOKUP($E11,Фонд!$A$2:$H$7,COLUMN(Fact_Инвестиции!D11),0) -> 1000 | X11: =VLOOKUP($E11,Фонд!$A$2:$H$7,COLUMN(Fact_Инвестиции!E11),0) -> RUB | Y11: =VLOOKUP($E11,Фонд!$A$2:$H$7,COLUMN(Fact_Инвестиции!F11),0) -> 47848 | Z11: =VLOOKUP($B11,Время!$A$2:$G$25,COLUMN(Fact_Инвестиции!B11),0) -> 45337 | AA11: =VLOOKUP($B11,Время!$A$2:$G$25,COLUMN(Fact_Инвестиции!C11),0) -> 2024 | AB11: =VLOOKUP($B11,Время!$A$2:$G$25,COLUMN(Fact_Инвестиции!D11),0) -> 1 | AC11: =VLOOKUP($B11,Время!$A$2:$G$25,COLUMN(Fact_Инвестиции!E11),0) -> 2 | AD11: =VLOOKUP($B11,Время!$A$2:$G$25,COLUMN(Fact_Инвестиции!F11),0) -> 15 | AE11: =VLOOKUP($B11,Время!$A$2:$G$25,COLUMN(Fact_Инвестиции!G11),0) -> Четверг
A12: 12 | B12: 20240215 | C12: 2 | D12: 1 | E12: 2 | F12: 53000 | G12: 2128.9 | H12: 112831700 | I12: 9.1 | J12: =VLOOKUP($D12,Инвестор!$A$2:$F$6,COLUMN(Fact_Инвестиции!B12),0) -> Физическое лицо | K12: =VLOOKUP($D12,Инвестор!$A$2:$F$6,COLUMN(Fact_Инвестиции!C12),0) -> 770112345678 | L12: =VLOOKUP($D12,Инвестор!$A$2:$F$6,COLUMN(Fact_Инвестиции!D12),0) -> Иванов Алексей Петрович | M12: =VLOOKUP($D12,Инвестор!$A$2:$F$6,COLUMN(Fact_Инвестиции!E12),0) -> Квалифицированный | N12: =VLOOKUP($D12,Инвестор!$A$2:$F$6,COLUMN(Fact_Инвестиции!F12),0) -> Москва | O12: =VLOOKUP($C12,Фонд!$A$2:$H$7,COLUMN(Fact_Инвестиции!B12),0) -> RU000A0JX0F2 | P12: =VLOOKUP($C12,Фонд!$A$2:$H$7,COLUMN(Fact_Инвестиции!C12),0) -> Газпромбанк-10 | Q12: =VLOOKUP($C12,Фонд!$A$2:$H$7,COLUMN(Fact_Инвестиции!D12),0) -> 1000 | R12: =VLOOKUP($C12,Фонд!$A$2:$H$7,COLUMN(Fact_Инвестиции!E12),0) -> RUB | S12: =VLOOKUP($C12,Фонд!$A$2:$H$7,COLUMN(Fact_Инвестиции!F12),0) -> 46888 | T12: =VLOOKUP($C12,Фонд!$A$2:$H$7,COLUMN(Fact_Инвестиции!G12),0) -> Корп. облигация | U12: =VLOOKUP($E12,Фонд!$A$2:$H$7,COLUMN(Fact_Инвестиции!B12),0) -> RU000A0JX0F2 | V12: =VLOOKUP($E12,Фонд!$A$2:$H$7,COLUMN(Fact_Инвестиции!C12),0) -> Газпромбанк-10 | W12: =VLOOKUP($E12,Фонд!$A$2:$H$7,COLUMN(Fact_Инвестиции!D12),0) -> 1000 | X12: =VLOOKUP($E12,Фонд!$A$2:$H$7,COLUMN(Fact_Инвестиции!E12),0) -> RUB | Y12: =VLOOKUP($E12,Фонд!$A$2:$H$7,COLUMN(Fact_Инвестиции!F12),0) -> 46888 | Z12: =VLOOKUP($B12,Время!$A$2:$G$25,COLUMN(Fact_Инвестиции!B12),0) -> 45337 | AA12: =VLOOKUP($B12,Время!$A$2:$G$25,COLUMN(Fact_Инвестиции!C12),0) -> 2024 | AB12: =VLOOKUP($B12,Время!$A$2:$G$25,COLUMN(Fact_Инвестиции!D12),0) -> 1 | AC12: =VLOOKUP($B12,Время!$A$2:$G$25,COLUMN(Fact_Инвестиции!E12),0) -> 2 | AD12: =VLOOKUP($B12,Время!$A$2:$G$25,COLUMN(Fact_Инвестиции!F12),0) -> 15 | AE12: =VLOOKUP($B12,Время!$A$2:$G$25,COLUMN(Fact_Инвестиции!G12),0) -> Четверг
A13: 13 | B13: 20240301 | C13: 3 | D13: 2 | E13: 3 | F13: 9000 | G13: 195.75 | H13: 1761750 | I13: 13.8 | J13: =VLOOKUP($D13,Инвестор!$A$2:$F$6,COLUMN(Fact_Инвестиции!B13),0) -> Юридическое лицо | K13: =VLOOKUP($D13,Инвестор!$A$2:$F$6,COLUMN(Fact_Инвестиции!C13),0) -> 770198765432 | L13: =VLOOKUP($D13,Инвестор!$A$2:$F$6,COLUMN(Fact_Инвестиции!D13),0) -> ООО "ИнвестПро" | M13: =VLOOKUP($D13,Инвестор!$A$2:$F$6,COLUMN(Fact_Инвестиции!E13),0) -> Профессиональный | N13: =VLOOKUP($D13,Инвестор!$A$2:$F$6,COLUMN(Fact_Инвестиции!F13),0) -> Санкт-Петербург | O13: =VLOOKUP($C13,Фонд!$A$2:$H$7,COLUMN(Fact_Инвестиции!B13),0) -> US0378331005 | P13: =VLOOKUP($C13,Фонд!$A$2:$H$7,COLUMN(Fact_Инвестиции!C13),0) -> Apple | Q13: =VLOOKUP($C13,Фонд!$A$2:$H$7,COLUMN(Fact_Инвестиции!D13),0) -> 0 | R13: =VLOOKUP($C13,Фонд!$A$2:$H$7,COLUMN(Fact_Инвестиции!E13),0) -> USD | S13: =VLOOKUP($C13,Фонд!$A$2:$H$7,COLUMN(Fact_Инвестиции!F13),0) -> 0 | T13: =VLOOKUP($C13,Фонд!$A$2:$H$7,COLUMN(Fact_Инвестиции!G13),0) -> Акция | U13: =VLOOKUP($E13,Фонд!$A$2:$H$7,COLUMN(Fact_Инвестиции!B13),0) -> US0378331005 | V13: =VLOOKUP($E13,Фонд!$A$2:$H$7,COLUMN(Fact_Инвестиции!C13),0) -> Apple | W13: =VLOOKUP($E13,Фонд!$A$2:$H$7,COLUMN(Fact_Инвестиции!D13),0) -> 0 | X13: =VLOOKUP($E13,Фонд!$A$2:$H$7,COLUMN(Fact_Инвестиции!E13),0) -> USD | Y13: =VLOOKUP($E13,Фонд!$A$2:$H$7,COLUMN(Fact_Инвестиции!F13),0) -> 0 | Z13: =VLOOKUP($B13,Время!$A$2:$G$25,COLUMN(Fact_Инвестиции!B13),0) -> 45294 | AA13: =VLOOKUP($B13,Время!$A$2:$G$25,COLUMN(Fact_Инвестиции!C13),0) -> 2024 | AB13: =VLOOKUP($B13,Время!$A$2:$G$25,COLUMN(Fact_Инвестиции!D13),0) -> 1 | AC13: =VLOOKUP($B13,Время!$A$2:$G$25,COLUMN(Fact_Инвестиции!E13),0) -> 3 | AD13: =VLOOKUP($B13,Время!$A$2:$G$25,COLUMN(Fact_Инвестиции!F13),0) -> 1 | AE13: =VLOOKUP($B13,Время!$A$2:$G$25,COLUMN(Fact_Инвестиции!G13),0) -> Пятница
... A41: 41 | B41: 20240101 | C41: 1 | D41: 1 | E41: 1 | F41: 10000 | G41: 1050.5 | H41: 10505000 | I41: 7.2 | J41: =VLOOKUP($D41,Инвестор!$A$2:$F$6,COLUMN(Fact_Инвестиции!B41),0) -> Физическое лицо | K41: =VLOOKUP($D41,Инвестор!$A$2:$F$6,COLUMN(Fact_Инвестиции!C41),0) -> 770112345678 | L41: =VLOOKUP($D41,Инвестор!$A$2:$F$6,COLUMN(Fact_Инвестиции!D41),0) -> Иванов Алексей Петрович | M41: =VLOOKUP($D41,Инвестор!$A$2:$F$6,COLUMN(Fact_Инвестиции!E41),0) -> Квалифицированный | N41: =VLOOKUP($D41,Инвестор!$A$2:$F$6,COLUMN(Fact_Инвестиции!F41),0) -> Москва | O41: =VLOOKUP($C41,Фонд!$A$2:$H$7,COLUMN(Fact_Инвестиции!B41),0) -> RU000A0JXYF1 | P41: =VLOOKUP($C41,Фонд!$A$2:$H$7,COLUMN(Fact_Инвестиции!C41),0) -> ОФЗ 26231 | Q41: =VLOOKUP($C41,Фонд!$A$2:$H$7,COLUMN(Fact_Инвестиции!D41),0) -> 1000 | R41: =VLOOKUP($C41,Фонд!$A$2:$H$7,COLUMN(Fact_Инвестиции!E41),0) -> RUB | S41: =VLOOKUP($C41,Фонд!$A$2:$H$7,COLUMN(Fact_Инвестиции!F41),0) -> 47848 | T41: =VLOOKUP($C41,Фонд!$A$2:$H$7,COLUMN(Fact_Инвестиции!G41),0) -> Гос. облигация | U41: =VLOOKUP($E41,Фонд!$A$2:$H$7,COLUMN(Fact_Инвестиции!B41),0) -> RU000A0JXYF1 | V41: =VLOOKUP($E41,Фонд!$A$2:$H$7,COLUMN(Fact_Инвестиции!C41),0) -> ОФЗ 26231 | W41: =VLOOKUP($E41,Фонд!$A$2:$H$7,COLUMN(Fact_Инвестиции!D41),0) -> 1000 | X41: =VLOOKUP($E41,Фонд!$A$2:$H$7,COLUMN(Fact_Инвестиции!E41),0) -> RUB | Y41: =VLOOKUP($E41,Фонд!$A$2:$H$7,COLUMN(Fact_Инвестиции!F41),0) -> 47848 | Z41: =VLOOKUP($B41,Время!$A$2:$G$25,COLUMN(Fact_Инвестиции!B41),0) -> 45292 | AA41: =VLOOKUP($B41,Время!$A$2:$G$25,COLUMN(Fact_Инвестиции!C41),0) -> 2024 | AB41: =VLOOKUP($B41,Время!$A$2:$G$25,COLUMN(Fact_Инвестиции!D41),0) -> 1 | AC41: =VLOOKUP($B41,Время!$A$2:$G$25,COLUMN(Fact_Инвестиции!E41),0) -> 1 | AD41: =VLOOKUP($B41,Время!$A$2:$G$25,COLUMN(Fact_Инвестиции!F41),0) -> 1 | AE41: =VLOOKUP($B41,Время!$A$2:$G$25,COLUMN(Fact_Инвестиции!G41),0) -> Понедельник

Sheet Фонд
A1: Код | B1: ISIN_FIGI | C1: Наименование | D1: Номинал | E1: ВалютаНоминала | F1: ДатаПогашения | G1: ТипБумаги | H1: КодЭмитента
A2: 1 | B2: RU000A0JXYF1 | C2: ОФЗ 26231 | D2: 1000 | E2: RUB | F2: 47848 | G2: Гос. облигация | H2: 6
A3: 2 | B3: RU000A0JX0F2 | C3: Газпромбанк-10 | D3: 1000 | E3: RUB | F3: 46888 | G3: Корп. облигация | H3: 1
A4: 3 | B4: US0378331005 | C4: Apple | D4: 0 | E4: USD | G4: Акция | H4: 4
A5: 4 | B5: US5949181045 | C5: Microsoft | D5: 0 | E5: USD | G5: Акция | H5: 5
A6: 5 | B6: RU000A0JXUF3 | C6: Сбербанк-5 | D6: 1000 | E6: RUB | F6: 47411 | G6: Корп. облигация | H6: 2
A7: 6 | B7: RU000A0JXVF4 | C7: ВТБ-7 | D7: 1000 | E7: RUB | F7: 46663 | G7: Корп. облигация | H7: 3

Sheet ЦеннаяБумага
A1: Код | B1: Название | C1: ISIN | D1: ДатаСоздания | E1: Статус | F1: Валюта | G1: КодВидаФонда
A2: 1 | B2: Фонд Ликвидность | C2: RU000A0JX123 | D2: 43831 | E2: активен | F2: RUB | G2: 1
A3: 2 | B3: Фонд Стабильность | C3: RU000A0JX456 | D3: 43539 | E3: активен | F3: RUB | G3: 2
A4: 3 | B4: Фонд Рост | C4: RU000A0JX789 | D4: 44475 | E4: активен | F4: USD | G4: 3
A5: 4 | B5: Фонд Баланс | C5: RU000A0JXABC | D5: 43231 | E5: активен | F5: RUB | G5: 4

Sheet Инвестор
A1: Код | B1: Тип | C1: Идентификатор | D1: Наименование_ФИО | E1: Категория | F1: Регион
A2: 1 | B2: Физическое лицо | C2: 770112345678 | D2: Иванов Алексей Петрович | E2: Квалифицированный | F2: Москва
A3: 2 | B3: Юридическое лицо | C3: 770198765432 | D3: ООО "ИнвестПро" | E3: Профессиональный | F3: Санкт-Петербург
A4: 3 | B4: Физическое лицо | C4: 770123456789 | D4: Смирнова Мария Игоревна | E4: Неквалифицированный | F4: Новосибирск
A5: 4 | B5: Юридическое лицо | C5: 770187654321 | D5: АО "КапиталТраст" | E5: Профессиональный | F5: Москва
A6: 5 | B6: Физическое лицо | C6: 770134567890 | D6: Кузнецов Дмитрий Сергеевич | E6: Квалифицированный | F6: Екатеринбург

Sheet Время
A1: КодВремени | B1: Дата | C1: Год | D1: Квартал | E1: Месяц | F1: День | G1: ДеньНедели
A2: 20240101 | B2: 45292 | C2: 2024 | D2: 1 | E2: 1 | F2: 1 | G2: Понедельник
A3: 20240115 | B3: 45306 | C3: 2024 | D3: 1 | E3: 1 | F3: 15 | G3: Понедельник
A4: 20240201 | B4: 45293 | C4: 2024 | D4: 1 | E4: 2 | F4: 1 | G4: Четверг
A5: 20240215 | B5: 45337 | C5: 2024 | D5: 1 | E5: 2 | F5: 15 | G5: Четверг
A6: 20240301 | B6: 45294 | C6: 2024 | D6: 1 | E6: 3 | F6: 1 | G6: Пятница
A7: 20240315 | B7: 45366 | C7: 2024 | D7: 1 | E7: 3 | F7: 15 | G7: Пятница
A8: 20240401 | B8: 45295 | C8: 2024 | D8: 2 | E8: 4 | F8: 1 | G8: Понедельник
A9: 20240415 | B9: 45397 | C9: 2024 | D9: 2 | E9: 4 | F9: 15 | G9: Понедельник
A10: 20240501 | B10: 45296 | C10: 2024 | D10: 2 | E10: 5 | F10: 1 | G10: Среда
A11: 20240515 | B11: 45427 | C11: 2024 | D11: 2 | E11: 5 | F11: 15 | G11: Среда
A12: 20240601 | B12: 45297 | C12: 2024 | D12: 2 | E12: 6 | F12: 1 | G12: Суббота
A13: 20240615 | B13: 45458 | C13: 2024 | D13: 2 | E13: 6 | F13: 15 | G13: Суббота
... A25: 20241215 | B25: 45641 | C25: 2024 | D25: 4 | E25: 12 | F25: 15 | G25: Воскресенье
